{
  "description": "OCR 文本上下文纠错规则。每条规则包含正则表达式和替换文本，按顺序依次应用到 OCR 结果上。",
  "usage": "编辑此文件即可扩充规则；也可通过 --ocr-corrections <file> 加载自定义规则（与基础规则合并）",
  "rules": [
    {"pattern": "性别[芝兰芳芙]", "replacement": "性别女", "note": "性别女常见误识别"},
    {"pattern": "性别[暮幕另罗量]", "replacement": "性别男", "note": "性别男常见误识别"},
    {"pattern": "年能", "replacement": "年龄", "note": "年龄误识别"},
    {"pattern": "(\\d)些(?=[，。、\\s\\n）)]|$)", "replacement": "\\1岁", "note": "数字后'岁'误为'些'"},
    {"pattern": "脑疵", "replacement": "脑疝", "note": "脑疝误识别"},
    {"pattern": "狭實", "replacement": "狭窄", "note": "狭窄误识别"},
    {"pattern": "(颅内|颈内|基底|冠状|椎)动脑", "replacement": "\\1动脉", "note": "动脉误为动脑"},
    {"pattern": "烹治", "replacement": "意识", "note": "意识误识别"},
    {"pattern": "降碍", "replacement": "障碍", "note": "障碍误识别"},
    {"pattern": "偏[備癱]", "replacement": "偏瘫", "note": "偏瘫误识别"},
    {"pattern": "[癲癫][癇癎痫]", "replacement": "癫痫", "note": "癫痫变体"},
    {"pattern": "大(面积?)脆板塞", "replacement": "大\\1脑梗塞", "note": "脑梗塞误识别"},
    {"pattern": "气產", "replacement": "气管", "note": "气管误识别"},
    {"pattern": "碱遐", "replacement": "减弱", "note": "体格检查-减弱"},
    {"pattern": "滅退", "replacement": "减退", "note": "体格检查-减退"},
    {"pattern": "过礅", "replacement": "过敏", "note": "过敏误识别"},
    {"pattern": "法阮", "replacement": "法院", "note": "法院误识别"},
    {"pattern": "叛决", "replacement": "判决", "note": "判决误识别"},
    {"pattern": "诉论", "replacement": "诉讼", "note": "诉讼误识别"},
    {"pattern": "答告人", "replacement": "被告人", "note": "被告人误识别"},
    {"pattern": "证剧(?=[，。、\\s\\n）)])", "replacement": "证据", "note": "证据误识别"},
    {"pattern": "沙库巴去", "replacement": "沙库巴曲", "note": "药名：曲误为去"},
    {"pattern": "在乙拉西坦", "replacement": "左乙拉西坦", "note": "药名：左误为在"},
    {"pattern": "气室切开", "replacement": "气管切开", "note": "气管误识别"},
    {"pattern": "湍謩捾醌", "replacement": "温馨提示", "note": "温馨提示乱码"},
    {"pattern": "继续继续", "replacement": "继续", "note": "重复词"},
    {"pattern": "改天册", "replacement": "改用天册", "note": "替加环素品牌名前缺动词"},
    {"pattern": "性别冬", "replacement": "性别女", "note": "性别女误识别"}
  ]
}
